{"authorDailyContributionsMap":{"ivlarson20":[{"date":"2025-10-24T00:00:00","commitResults":[{"hash":"972df5f8c0cd53c9d5a256f128ccbb4f4a9035af","isMergeCommit":true,"messageTitle":"Merge pull request #8 from NYU-CSE-Software-Engineering/messaging-feature","messageBody":"Owner Renter Communication Feature","fileTypesAndContributionMap":{}}]}],"kylejjh":[],"lcm9995":[{"date":"2025-10-24T00:00:00","commitResults":[{"hash":"a0d8950c95c3a53db4078e36a29a0592f74b0dbf","isMergeCommit":false,"messageTitle":"added all deliverables for BDD assignment","messageBody":"","fileTypesAndContributionMap":{"md":{"insertions":23,"deletions":0}}},{"hash":"dbbf354f2bd90dd64e5c016d2d3eb16dc3fa2a47","isMergeCommit":true,"messageTitle":"Merge pull request #5 from NYU-CSE-Software-Engineering/lily_item_search","messageBody":"added all deliverables for BDD assignment","fileTypesAndContributionMap":{}}]}],"sulphemi":[{"date":"2025-10-24T00:00:00","commitResults":[{"hash":"dd025251f9218689a5bdfadba485629592960f67","isMergeCommit":false,"messageTitle":"add bdd feature description for account creation (#7)","messageBody":"* add account creation user story and gherkin\n\n* step definition for account creation\n\n* add note to model plan","fileTypesAndContributionMap":{"md":{"insertions":34,"deletions":0}}}]},{"date":"2025-10-25T00:00:00","commitResults":[{"hash":"58d37e8b0d993756a4045025d31847c19e028372","isMergeCommit":false,"messageTitle":"move misplaced file \"/item_upload.md\" to \"docs/item_upload.md\" (#11)","messageBody":"","fileTypesAndContributionMap":{"md":{"insertions":0,"deletions":0}}}]}],"sufyanw":[{"date":"2025-10-24T00:00:00","commitResults":[{"hash":"3adcf7703674c77110d4c0d66149d70502a9b18c","isMergeCommit":true,"messageTitle":"Merge pull request #3 from NYU-CSE-Software-Engineering/payments-kyle","messageBody":"Payments Kyle — Task 1–4 Deliverables","fileTypesAndContributionMap":{}},{"hash":"6485c53e8c071da5ddf956bb27dae8a56fe1c375","isMergeCommit":false,"messageTitle":"Set up new app, fix formatting","messageBody":"","fileTypesAndContributionMap":{"txt":{"insertions":1,"deletions":0},"md":{"insertions":24,"deletions":0}}},{"hash":"b3c7ab204d52af6195d774d7d46553df5e9ca32a","isMergeCommit":false,"messageTitle":"Sufyan\u0027s Changes: BDD For Administrative Powers, Setting up app repo","messageBody":"","fileTypesAndContributionMap":{"md":{"insertions":60,"deletions":0}}},{"hash":"4496a9abf500a266634e60b768389f8be92fc61d","isMergeCommit":true,"messageTitle":"Merge pull request #4 from NYU-CSE-Software-Engineering/admin","messageBody":"Sufyan\u0027s Changes: BDD For Administrative Powers, Setting up app repo","fileTypesAndContributionMap":{}}]},{"date":"2025-12-01T00:00:00","commitResults":[{"hash":"5a11674c93473299e322c59a0facd8a3d047dacd","isMergeCommit":false,"messageTitle":"Updated README.md","messageBody":"","fileTypesAndContributionMap":{"md":{"insertions":155,"deletions":13}}},{"hash":"711078eb2db670d6d5d3e97d324962aaed5f63eb","isMergeCommit":false,"messageTitle":"Revert \"Updated README.md\"","messageBody":"This reverts commit 5a11674c93473299e322c59a0facd8a3d047dacd.\n","fileTypesAndContributionMap":{"md":{"insertions":13,"deletions":155}}},{"hash":"abc3b204988d0c643533b7346ede40f7018ff24f","isMergeCommit":false,"messageTitle":"Updated README.md","messageBody":"","fileTypesAndContributionMap":{"md":{"insertions":155,"deletions":13}}},{"hash":"53bda21ea23eeb94b7dfab6290442945e161472e","isMergeCommit":true,"messageTitle":"Merge pull request #27 from NYU-CSE-Software-Engineering/readme","messageBody":"Updated README.md for Final Deliverable ","fileTypesAndContributionMap":{}}]}],"eh3323":[{"date":"2025-10-25T00:00:00","commitResults":[{"hash":"14539c05a1098aeab3028843998c4154b5ddfb24","isMergeCommit":true,"messageTitle":"Merge pull request #10 from NYU-CSE-Software-Engineering/bdd-item-upload","messageBody":"BDD Assignment: Add item upload feature specification","fileTypesAndContributionMap":{}}]}]},"authorFileTypeContributionMap":{"ivlarson20":{"java":0,"md":0,"fxml":0,"sh":0,"bat":0,"gradle":0,"txt":0},"kylejjh":{"java":0,"md":0,"fxml":0,"sh":0,"bat":0,"gradle":0,"txt":0},"lcm9995":{"java":0,"md":23,"fxml":0,"sh":0,"bat":0,"gradle":0,"txt":0},"sulphemi":{"java":0,"md":34,"fxml":0,"sh":0,"bat":0,"gradle":0,"txt":0},"sufyanw":{"java":0,"md":84,"fxml":0,"sh":0,"bat":0,"gradle":0,"txt":1},"eh3323":{"java":0,"md":0,"fxml":0,"sh":0,"bat":0,"gradle":0,"txt":0}},"authorContributionVariance":{"ivlarson20":0.0,"kylejjh":0.0,"lcm9995":5.6875,"sulphemi":12.428647,"sufyanw":2798.5886,"eh3323":0.0},"authorDisplayNameMap":{"ivlarson20":"ivlarson20","kylejjh":"kylejjh","lcm9995":"lcm9995","sulphemi":"sulphemi","sufyanw":"sufyanw","eh3323":"eh3323"}}
